{
  "columns": [
    { "key": "program", "label": "Program", "sortable": true },
    { "key": "partNumber", "label": "Part Number", "sortable": true, "editable": true },
    { "key": "partDescription", "label": "Part Description", "sortable": true, "editable": true },
    { "key": "materialStage", "label": "Material Stage", "sortable": true, "editable": true },
    { "key": "Jan-2026", "label": "Jan 2026", "sortable": true, "editable": true },
    { "key": "Feb-2026", "label": "Feb 2026", "sortable": true, "editable": true },
    { "key": "Mar-2026", "label": "Mar 2026", "sortable": true, "editable": true },
    { "key": "Apr-2026", "label": "Apr 2026", "sortable": true, "editable": true },
    { "key": "May-2026", "label": "May 2026", "sortable": true, "editable": true },
    { "key": "Jun-2026", "label": "Jun 2026", "sortable": true, "editable": true },
    { "key": "Jul-2026", "label": "Jul 2026", "sortable": true, "editable": true },
    { "key": "Aug-2026", "label": "Aug 2026", "sortable": true, "editable": true },
    { "key": "Sep-2026", "label": "Sep 2026", "sortable": true, "editable": true },
    { "key": "Oct-2026", "label": "Oct 2026", "sortable": true, "editable": true },
    { "key": "Nov-2026", "label": "Nov 2026", "sortable": true, "editable": true },
    { "key": "Dec-2026", "label": "Dec 2026", "sortable": true, "editable": true },
    { "key": "Jan-2027", "label": "Jan 2027", "sortable": true, "editable": true },
    { "key": "Feb-2027", "label": "Feb 2027", "sortable": true, "editable": true },
    { "key": "Mar-2027", "label": "Mar 2027", "sortable": true, "editable": true },
    { "key": "Apr-2027", "label": "Apr 2027", "sortable": true, "editable": true },
    { "key": "May-2027", "label": "May 2027", "sortable": true, "editable": true },
    { "key": "Jun-2027", "label": "Jun 2027", "sortable": true, "editable": true },
    { "key": "Jul-2027", "label": "Jul 2027", "sortable": true, "editable": true },
    { "key": "Aug-2027", "label": "Aug 2027", "sortable": true, "editable": true },
    { "key": "Sep-2027", "label": "Sep 2027", "sortable": true, "editable": true },
    { "key": "Oct-2027", "label": "Oct 2027", "sortable": true, "editable": true },
    { "key": "Nov-2027", "label": "Nov 2027", "sortable": true, "editable": true },
    { "key": "Dec-2027", "label": "Dec 2027", "sortable": true, "editable": true },
    { "key": "Jan-2028", "label": "Jan 2028", "sortable": true, "editable": true },
    { "key": "Feb-2028", "label": "Feb 2028", "sortable": true, "editable": true },
    { "key": "Mar-2028", "label": "Mar 2028", "sortable": true, "editable": true },
    { "key": "Apr-2028", "label": "Apr 2028", "sortable": true, "editable": true },
    { "key": "May-2028", "label": "May 2028", "sortable": true, "editable": true },
    { "key": "Jun-2028", "label": "Jun 2028", "sortable": true, "editable": true },
    { "key": "Jul-2028", "label": "Jul 2028", "sortable": true, "editable": true },
    { "key": "Aug-2028", "label": "Aug 2028", "sortable": true, "editable": true },
    { "key": "Sep-2028", "label": "Sep 2028", "sortable": true, "editable": true },
    { "key": "Oct-2028", "label": "Oct 2028", "sortable": true, "editable": true },
    { "key": "Nov-2028", "label": "Nov 2028", "sortable": true, "editable": true },
    { "key": "Dec-2028", "label": "Dec 2028", "sortable": true, "editable": true }
  ],
  "data": [
    {
      "program": "GS-5423",
      "partNumber": "PC-12723",
      "partDescription": "XXXX",
      "materialStage": "DP",
      "Jan-2026": 34, "Feb-2026": 41, "Mar-2026": 39, "Apr-2026": 45, "May-2026": 52, "Jun-2026": 48,
      "Jul-2026": 55, "Aug-2026": 61, "Sep-2026": 59, "Oct-2026": 63, "Nov-2026": 66, "Dec-2026": 71,
      "Jan-2027": 68, "Feb-2027": 72, "Mar-2027": 70, "Apr-2027": 75, "May-2027": 79, "Jun-2027": 83,
      "Jul-2027": 81, "Aug-2027": 84, "Sep-2027": 88, "Oct-2027": 90, "Nov-2027": 92, "Dec-2027": 95,
      "Jan-2028": 97, "Feb-2028": 100, "Mar-2028": 103, "Apr-2028": 105, "May-2028": 108, "Jun-2028": 110,
      "Jul-2028": 112, "Aug-2028": 115, "Sep-2028": 118, "Oct-2028": 120, "Nov-2028": 123, "Dec-2028": 126
    },
    {
      "program": "GS-5423",
      "partNumber": "PC-13296",
      "partDescription": "XXXX",
      "materialStage": "DP",
      "Jan-2026": 22, "Feb-2026": 25, "Mar-2026": 28, "Apr-2026": 32, "May-2026": 36, "Jun-2026": 39,
      "Jul-2026": 42, "Aug-2026": 46, "Sep-2026": 48, "Oct-2026": 51, "Nov-2026": 54, "Dec-2026": 58,
      "Jan-2027": 60, "Feb-2027": 63, "Mar-2027": 65, "Apr-2027": 67, "May-2027": 70, "Jun-2027": 72,
      "Jul-2027": 74, "Aug-2027": 76, "Sep-2027": 79, "Oct-2027": 82, "Nov-2027": 84, "Dec-2027": 87,
      "Jan-2028": 89, "Feb-2028": 92, "Mar-2028": 95, "Apr-2028": 97, "May-2028": 100, "Jun-2028": 103,
      "Jul-2028": 105, "Aug-2028": 108, "Sep-2028": 110, "Oct-2028": 113, "Nov-2028": 115, "Dec-2028": 118
    },

    {
      "program": "GS-5423",
      "partNumber": "IP-14478",
      "partDescription": "XXXX",
      "materialStage": "DS",
      "Jan-2026": 15, "Feb-2026": 18, "Mar-2026": 20, "Apr-2026": 24, "May-2026": 27, "Jun-2026": 29,
      "Jul-2026": 31, "Aug-2026": 34, "Sep-2026": 36, "Oct-2026": 39, "Nov-2026": 42, "Dec-2026": 45,
      "Jan-2027": 47, "Feb-2027": 49, "Mar-2027": 52, "Apr-2027": 55, "May-2027": 57, "Jun-2027": 60,
      "Jul-2027": 63, "Aug-2027": 65, "Sep-2027": 68, "Oct-2027": 70, "Nov-2027": 73, "Dec-2027": 75,
      "Jan-2028": 78, "Feb-2028": 80, "Mar-2028": 83, "Apr-2028": 86, "May-2028": 88, "Jun-2028": 91,
      "Jul-2028": 94, "Aug-2028": 96, "Sep-2028": 99, "Oct-2028": 102, "Nov-2028": 104, "Dec-2028": 107
    },
    {
      "program": "GS-5423",
      "partNumber": "PC-12723",
      "partDescription": "XXXX",
      "materialStage": "DP",
      "Jan-2026": 34,"Feb-2026": 41,"Mar-2026": 39,"Apr-2026": 45,"May-2026": 52,"Jun-2026": 48,
      "Jul-2026": 55,"Aug-2026": 61,"Sep-2026": 59,"Oct-2026": 63,"Nov-2026": 66,"Dec-2026": 71,
      "Jan-2027": 68,"Feb-2027": 72,"Mar-2027": 70,"Apr-2027": 75,"May-2027": 79,"Jun-2027": 83,
      "Jul-2027": 81,"Aug-2027": 84,"Sep-2027": 88,"Oct-2027": 90,"Nov-2027": 92,"Dec-2027": 95,
      "Jan-2028": 97,"Feb-2028": 100,"Mar-2028": 103,"Apr-2028": 105,"May-2028": 108,"Jun-2028": 110,
      "Jul-2028": 112,"Aug-2028": 115,"Sep-2028": 118,"Oct-2028": 120,"Nov-2028": 123,"Dec-2028": 126
    },
    {
      "program": "GS-5423",
      "partNumber": "PC-13296",
      "partDescription": "XXXX",
      "materialStage": "DP",
      "Jan-2026": 22,"Feb-2026": 25,"Mar-2026": 28,"Apr-2026": 32,"May-2026": 36,"Jun-2026": 39,
      "Jul-2026": 42,"Aug-2026": 46,"Sep-2026": 48,"Oct-2026": 51,"Nov-2026": 54,"Dec-2026": 58,
      "Jan-2027": 60,"Feb-2027": 63,"Mar-2027": 65,"Apr-2027": 67,"May-2027": 70,"Jun-2027": 72,
      "Jul-2027": 74,"Aug-2027": 76,"Sep-2027": 79,"Oct-2027": 82,"Nov-2027": 84,"Dec-2027": 87,
      "Jan-2028": 89,"Feb-2028": 92,"Mar-2028": 95,"Apr-2028": 97,"May-2028": 100,"Jun-2028": 103,
      "Jul-2028": 105,"Aug-2028": 108,"Sep-2028": 110,"Oct-2028": 113,"Nov-2028": 115,"Dec-2028": 118
    },
    {
      "program": "GS-5423",
      "partNumber": "IP-14478",
      "partDescription": "XXXX",
      "materialStage": "DS",
      "Jan-2026": 15,"Feb-2026": 18,"Mar-2026": 20,"Apr-2026": 24,"May-2026": 27,"Jun-2026": 29,
      "Jul-2026": 31,"Aug-2026": 34,"Sep-2026": 36,"Oct-2026": 39,"Nov-2026": 42,"Dec-2026": 45,
      "Jan-2027": 47,"Feb-2027": 49,"Mar-2027": 52,"Apr-2027": 55,"May-2027": 57,"Jun-2027": 60,
      "Jul-2027": 63,"Aug-2027": 65,"Sep-2027": 68,"Oct-2027": 70,"Nov-2027": 73,"Dec-2027": 75,
      "Jan-2028": 78,"Feb-2028": 80,"Mar-2028": 83,"Apr-2028": 86,"May-2028": 88,"Jun-2028": 91,
      "Jul-2028": 94,"Aug-2028": 96,"Sep-2028": 99,"Oct-2028": 102,"Nov-2028": 104,"Dec-2028": 107
    },
    {
      "program": "GS-5423",
      "partNumber": "IP-15699",
      "partDescription": "XXXX",
      "materialStage": "DS",
      "Jan-2026": 18,"Feb-2026": 21,"Mar-2026": 23,"Apr-2026": 27,"May-2026": 30,"Jun-2026": 33,
      "Jul-2026": 36,"Aug-2026": 39,"Sep-2026": 41,"Oct-2026": 44,"Nov-2026": 47,"Dec-2026": 50,
      "Jan-2027": 53,"Feb-2027": 55,"Mar-2027": 58,"Apr-2027": 60,"May-2027": 63,"Jun-2027": 66,
      "Jul-2027": 69,"Aug-2027": 72,"Sep-2027": 74,"Oct-2027": 77,"Nov-2027": 80,"Dec-2027": 83,
      "Jan-2028": 86,"Feb-2028": 89,"Mar-2028": 92,"Apr-2028": 95,"May-2028": 97,"Jun-2028": 100,
      "Jul-2028": 103,"Aug-2028": 106,"Sep-2028": 109,"Oct-2028": 112,"Nov-2028": 115,"Dec-2028": 118
    },

    {
      "program": "GS-2872",
      "partNumber": "PC-12742",
      "partDescription": "XXXX",
      "materialStage": "DP",
      "Jan-2026": 25,"Feb-2026": 28,"Mar-2026": 31,"Apr-2026": 35,"May-2026": 38,"Jun-2026": 41,
      "Jul-2026": 44,"Aug-2026": 47,"Sep-2026": 50,"Oct-2026": 53,"Nov-2026": 56,"Dec-2026": 59,
      "Jan-2027": 61,"Feb-2027": 64,"Mar-2027": 67,"Apr-2027": 70,"May-2027": 72,"Jun-2027": 75,
      "Jul-2027": 78,"Aug-2027": 81,"Sep-2027": 84,"Oct-2027": 87,"Nov-2027": 90,"Dec-2027": 93,
      "Jan-2028": 96,"Feb-2028": 99,"Mar-2028": 102,"Apr-2028": 105,"May-2028": 108,"Jun-2028": 111,
      "Jul-2028": 114,"Aug-2028": 117,"Sep-2028": 120,"Oct-2028": 123,"Nov-2028": 126,"Dec-2028": 129
    },
    {
      "program": "GS-2872",
      "partNumber": "PC-12777",
      "partDescription": "XXXX",
      "materialStage": "DP",
      "Jan-2026": 27,"Feb-2026": 30,"Mar-2026": 33,"Apr-2026": 36,"May-2026": 40,"Jun-2026": 43,
      "Jul-2026": 46,"Aug-2026": 49,"Sep-2026": 52,"Oct-2026": 55,"Nov-2026": 58,"Dec-2026": 61,
      "Jan-2027": 64,"Feb-2027": 67,"Mar-2027": 70,"Apr-2027": 73,"May-2027": 76,"Jun-2027": 79,
      "Jul-2027": 82,"Aug-2027": 85,"Sep-2027": 88,"Oct-2027": 91,"Nov-2027": 94,"Dec-2027": 97,
      "Jan-2028": 100,"Feb-2028": 103,"Mar-2028": 106,"Apr-2028": 109,"May-2028": 112,"Jun-2028": 115,
      "Jul-2028": 118,"Aug-2028": 121,"Sep-2028": 124,"Oct-2028": 127,"Nov-2028": 130,"Dec-2028": 133
    },
    {
      "program": "GS-2872",
      "partNumber": "PC-13294",
      "partDescription": "XXXX",
      "materialStage": "DP",
      "Jan-2026": 29,"Feb-2026": 32,"Mar-2026": 35,"Apr-2026": 38,"May-2026": 41,"Jun-2026": 44,
      "Jul-2026": 47,"Aug-2026": 50,"Sep-2026": 53,"Oct-2026": 56,"Nov-2026": 59,"Dec-2026": 62,
      "Jan-2027": 65,"Feb-2027": 68,"Mar-2027": 71,"Apr-2027": 74,"May-2027": 77,"Jun-2027": 80,
      "Jul-2027": 83,"Aug-2027": 86,"Sep-2027": 89,"Oct-2027": 92,"Nov-2027": 95,"Dec-2027": 98,
      "Jan-2028": 101,"Feb-2028": 104,"Mar-2028": 107,"Apr-2028": 110,"May-2028": 113,"Jun-2028": 116,
      "Jul-2028": 119,"Aug-2028": 122,"Sep-2028": 125,"Oct-2028": 128,"Nov-2028": 131,"Dec-2028": 134
    },
    {
      "program": "GS-2872",
      "partNumber": "IP-14799",
      "partDescription": "XXXX",
      "materialStage": "DS",
      "Jan-2026": 20,"Feb-2026": 23,"Mar-2026": 26,"Apr-2026": 29,"May-2026": 32,"Jun-2026": 35,
      "Jul-2026": 38,"Aug-2026": 41,"Sep-2026": 44,"Oct-2026": 47,"Nov-2026": 50,"Dec-2026": 53,
      "Jan-2027": 56,"Feb-2027": 59,"Mar-2027": 62,"Apr-2027": 65,"May-2027": 68,"Jun-2027": 71,
      "Jul-2027": 74,"Aug-2027": 77,"Sep-2027": 80,"Oct-2027": 83,"Nov-2027": 86,"Dec-2027": 89,
      "Jan-2028": 92,"Feb-2028": 95,"Mar-2028": 98,"Apr-2028": 101,"May-2028": 104,"Jun-2028": 107,
      "Jul-2028": 110,"Aug-2028": 113,"Sep-2028": 116,"Oct-2028": 119,"Nov-2028": 122,"Dec-2028": 125
    },
    {
      "program": "GS-2872",
      "partNumber": "IP-15732",
      "partDescription": "XXXX",
      "materialStage": "DS",
      "Jan-2026": 19,"Feb-2026": 22,"Mar-2026": 25,"Apr-2026": 28,"May-2026": 31,"Jun-2026": 34,
      "Jul-2026": 37,"Aug-2026": 40,"Sep-2026": 43,"Oct-2026": 46,"Nov-2026": 49,"Dec-2026": 52,
      "Jan-2027": 55,"Feb-2027": 58,"Mar-2027": 61,"Apr-2027": 64,"May-2027": 67,"Jun-2027": 70,
      "Jul-2027": 73,"Aug-2027": 76,"Sep-2027": 79,"Oct-2027": 82,"Nov-2027": 85,"Dec-2027": 88,
      "Jan-2028": 91,"Feb-2028": 94,"Mar-2028": 97,"Apr-2028": 100,"May-2028": 103,"Jun-2028": 106,
      "Jul-2028": 109,"Aug-2028": 112,"Sep-2028": 115,"Oct-2028": 118,"Nov-2028": 121,"Dec-2028": 124
    },

    {
      "program": "GS-4321",
      "partNumber": "PC-13163",
      "partDescription": "XXXX",
      "materialStage": "DP",
      "Jan-2026": 30,"Feb-2026": 33,"Mar-2026": 36,"Apr-2026": 39,"May-2026": 42,"Jun-2026": 45,
      "Jul-2026": 48,"Aug-2026": 51,"Sep-2026": 54,"Oct-2026": 57,"Nov-2026": 60,"Dec-2026": 63,
      "Jan-2027": 66,"Feb-2027": 69,"Mar-2027": 72,"Apr-2027": 75,"May-2027": 78,"Jun-2027": 81,
      "Jul-2027": 84,"Aug-2027": 87,"Sep-2027": 90,"Oct-2027": 93,"Nov-2027": 96,"Dec-2027": 99,
      "Jan-2028": 102,"Feb-2028": 105,"Mar-2028": 108,"Apr-2028": 111,"May-2028": 114,"Jun-2028": 117,
      "Jul-2028": 120,"Aug-2028": 123,"Sep-2028": 126,"Oct-2028": 129,"Nov-2028": 132,"Dec-2028": 135
    },
    {
      "program": "GS-4321",
      "partNumber": "PC-13164",
      "partDescription": "XXXX",
      "materialStage": "DP",
      "Jan-2026": 31,"Feb-2026": 34,"Mar-2026": 37,"Apr-2026": 40,"May-2026": 43,"Jun-2026": 46,
      "Jul-2026": 49,"Aug-2026": 52,"Sep-2026": 55,"Oct-2026": 58,"Nov-2026": 61,"Dec-2026": 64,
      "Jan-2027": 67,"Feb-2027": 70,"Mar-2027": 73,"Apr-2027": 76,"May-2027": 79,"Jun-2027": 82,
      "Jul-2027": 85,"Aug-2027": 88,"Sep-2027": 91,"Oct-2027": 94,"Nov-2027": 97,"Dec-2027": 100,
      "Jan-2028": 103,"Feb-2028": 106,"Mar-2028": 109,"Apr-2028": 112,"May-2028": 115,"Jun-2028": 118,
      "Jul-2028": 121,"Aug-2028": 124,"Sep-2028": 127,"Oct-2028": 130,"Nov-2028": 133,"Dec-2028": 136
    },
    {
      "program": "GS-4321",
      "partNumber": "IP-15236",
      "partDescription": "XXXX",
      "materialStage": "DS",
      "Jan-2026": 21,"Feb-2026": 24,"Mar-2026": 27,"Apr-2026": 30,"May-2026": 33,"Jun-2026": 36,
      "Jul-2026": 39,"Aug-2026": 42,"Sep-2026": 45,"Oct-2026": 48,"Nov-2026": 51,"Dec-2026": 54,
      "Jan-2027": 57,"Feb-2027": 60,"Mar-2027": 63,"Apr-2027": 66,"May-2027": 69,"Jun-2027": 72,
      "Jul-2027": 75,"Aug-2027": 78,"Sep-2027": 81,"Oct-2027": 84,"Nov-2027": 87,"Dec-2027": 90,
      "Jan-2028": 93,"Feb-2028": 96,"Mar-2028": 99,"Apr-2028": 102,"May-2028": 105,"Jun-2028": 108,
      "Jul-2028": 111,"Aug-2028": 114,"Sep-2028": 117,"Oct-2028": 120,"Nov-2028": 123,"Dec-2028": 126
    },

    {
      "program": "GS-0151",
      "partNumber": "PC-13032",
      "partDescription": "XXXX",
      "materialStage": "DP",
      "Jan-2026": 26,"Feb-2026": 29,"Mar-2026": 32,"Apr-2026": 35,"May-2026": 38,"Jun-2026": 41,
      "Jul-2026": 44,"Aug-2026": 47,"Sep-2026": 50,"Oct-2026": 53,"Nov-2026": 56,"Dec-2026": 59,
      "Jan-2027": 62,"Feb-2027": 65,"Mar-2027": 68,"Apr-2027": 71,"May-2027": 74,"Jun-2027": 77,
      "Jul-2027": 80,"Aug-2027": 83,"Sep-2027": 86,"Oct-2027": 89,"Nov-2027": 92,"Dec-2027": 95,
      "Jan-2028": 98,"Feb-2028": 101,"Mar-2028": 104,"Apr-2028": 107,"May-2028": 110,"Jun-2028": 113,
      "Jul-2028": 116,"Aug-2028": 119,"Sep-2028": 122,"Oct-2028": 125,"Nov-2028": 128,"Dec-2028": 131
    },
    {
      "program": "GS-0151",
      "partNumber": "PC-13058",
      "partDescription": "XXXX",
      "materialStage": "DP",
      "Jan-2026": 28,"Feb-2026": 31,"Mar-2026": 34,"Apr-2026": 37,"May-2026": 40,"Jun-2026": 43,
      "Jul-2026": 46,"Aug-2026": 49,"Sep-2026": 52,"Oct-2026": 55,"Nov-2026": 58,"Dec-2026": 61,
      "Jan-2027": 64,"Feb-2027": 67,"Mar-2027": 70,"Apr-2027": 73,"May-2027": 76,"Jun-2027": 79,
      "Jul-2027": 82,"Aug-2027": 85,"Sep-2027": 88,"Oct-2027": 91,"Nov-2027": 94,"Dec-2027": 97,
      "Jan-2028": 100,"Feb-2028": 103,"Mar-2028": 106,"Apr-2028": 109,"May-2028": 112,"Jun-2028": 115,
      "Jul-2028": 118,"Aug-2028": 121,"Sep-2028": 124,"Oct-2028": 127,"Nov-2028": 130,"Dec-2028": 133
    },
    {
      "program": "GS-0151",
      "partNumber": "IP-15168",
      "partDescription": "XXXX",
      "materialStage": "DS",
      "Jan-2026": 17,"Feb-2026": 20,"Mar-2026": 23,"Apr-2026": 26,"May-2026": 29,"Jun-2026": 32,
      "Jul-2026": 35,"Aug-2026": 38,"Sep-2026": 41,"Oct-2026": 44,"Nov-2026": 47,"Dec-2026": 50,
      "Jan-2027": 53,"Feb-2027": 56,"Mar-2027": 59,"Apr-2027": 62,"May-2027": 65,"Jun-2027": 68,
      "Jul-2027": 71,"Aug-2027": 74,"Sep-2027": 77,"Oct-2027": 80,"Nov-2027": 83,"Dec-2027": 86,
      "Jan-2028": 89,"Feb-2028": 92,"Mar-2028": 95,"Apr-2028": 98,"May-2028": 101,"Jun-2028": 104,
      "Jul-2028": 107,"Aug-2028": 110,"Sep-2028": 113,"Oct-2028": 116,"Nov-2028": 119,"Dec-2028": 122
    }

  ]
}